playground/__init__.py
playground/config.py
playground/fs.py
lakefs_playground_utils-0.0.14.dist-info/LICENSE
lakefs_playground_utils-0.0.14.dist-info/METADATA
lakefs_playground_utils-0.0.14.dist-info/NOTICE
lakefs_playground_utils-0.0.14.dist-info/WHEEL
lakefs_playground_utils-0.0.14.dist-info/top_level.txt
lakefs_playground_utils-0.0.14.dist-info/RECORD
