Metadata-Version: 2.1
Name: lakefs-playground-utils
Version: 0.0.14
Summary: lakeFS Playground Utilities
Home-page: https://github.com/treeverse/lakefs-playground-utils
Author: Or Tzabary
Author-email: or.tzabary@treeverse.io
License: Apache 2.0
Keywords: lakefs playground
Platform: any
License-File: LICENSE
License-File: NOTICE
Requires-Dist: fsspec (>=2021.11.0)
Requires-Dist: requests (>=2.0.0)
Requires-Dist: lakefs-client (>=0.85.0)
Requires-Dist: email-validator (==1.3.0)
Requires-Dist: PyYAML (>=6.0)
